{
	"timestamp": "Fri Apr 18 10:52:57 2014",
	"org_type": "school",
	"org_name": "Peabody Elementary School",
	"report_card": {
		"sections": [
			{
				"id": "accountability",
				"data": [null
				]
			},
			{
				"id": "dccas",
				"data": [

				]
			},
			{
				"id": "amo_targets",
				"data": [

				]
			},
			{
				"id": "hqt_status",
				"data":0.889
			},
			{
				"id": "early_childhood",
				"data": [

				]
			},
			{
				"id": "college_enroll",
				"data": [
				]
			},
			{
				"id": "graduation",
				"data": [


				]
			}
		]
	 },


	"profile": {
		"sections": [
			{
				"id": "program_info",
				"data": ["•Tippi Toes Dance (After School Program)",
"Alliance for Healthy Schools",
"Arts for Every Student",
"DC Arts and Humanities Education Collaborative",
"Edible Gardens",
"Girl Scouts",
"HomeDo (After School Program)",
"Joe's Den (Before and After School Program)",
"Labyrinth Games",
"Language Stars (After School Program)",
"Rita's Place (Before and After School Program)",
"Smithsonian EdLAb",
"Spanish After school program",
"Story of Food (classroom cooking)",
"The Phillips Collection",
"Tippi Toes Dance (After School Program)",
"Whole Foods Salad Bar"
				]
			},
			{
				"id": "enrollment",
				"data": [
					{
						"key": {"grade": "All", "subgroup": "All", "year": "2011"},
						"val": 234
					},
					{
						"key": {"grade": "All", "subgroup": "African American", "year": "2011"},
						"val": 84
					},
					{
						"key": {"grade": "All", "subgroup": "White", "year": "2011"},
						"val": 114
					},
					{
						"key": {"grade": "All", "subgroup": "Asian", "year": "2011"},
						"val": 12
					},
					{
						"key": {"grade": "All", "subgroup": "Multi Racial", "year": "2011"},
						"val": 15
					},
					{
						"key": {"grade": "All", "subgroup": "Special Education", "year": "2011"},
						"val": 16
					},
					{
						"key": {"grade": "All", "subgroup": "Economically Disadvantaged", "year": "2011"},
						"val": 48
					},
					{
						"key": {"grade": "All", "subgroup": "Male", "year": "2011"},
						"val": 113
					},
					{
						"key": {"grade": "All", "subgroup": "Female", "year": "2011"},
						"val": 121
					},
					{
						"key": {"grade": "KG", "subgroup": "All", "year": "2011"},
						"val": 103
					},
					{
						"key": {"grade": "KG", "subgroup": "African American", "year": "2011"},
						"val": 44
					},
					{
						"key": {"grade": "KG", "subgroup": "White", "year": "2011"},
						"val": 40
					},
					{
						"key": {"grade": "KG", "subgroup": "Economically Disadvantaged", "year": "2011"},
						"val": 22
					},
					{
						"key": {"grade": "KG", "subgroup": "Male", "year": "2011"},
						"val": 52
					},
					{
						"key": {"grade": "KG", "subgroup": "Female", "year": "2011"},
						"val": 51
					},
					{
						"key": {"grade": "PK", "subgroup": "All", "year": "2011"},
						"val": 100
					},
					{
						"key": {"grade": "PK", "subgroup": "African American", "year": "2011"},
						"val": 35
					},
					{
						"key": {"grade": "PK", "subgroup": "White", "year": "2011"},
						"val": 54
					},
					{
						"key": {"grade": "PK", "subgroup": "Economically Disadvantaged", "year": "2011"},
						"val": 22
					},
					{
						"key": {"grade": "PK", "subgroup": "Male", "year": "2011"},
						"val": 47
					},
					{
						"key": {"grade": "PK", "subgroup": "Female", "year": "2011"},
						"val": 53
					},
					{
						"key": {"grade": "PS", "subgroup": "All", "year": "2011"},
						"val": 31
					},
					{
						"key": {"grade": "PS", "subgroup": "White", "year": "2011"},
						"val": 20
					},
					{
						"key": {"grade": "PS", "subgroup": "Male", "year": "2011"},
						"val": 14
					},
					{
						"key": {"grade": "PS", "subgroup": "Female", "year": "2011"},
						"val": 17
					},
					{
						"key": {"grade": "All", "subgroup": "All", "year": "2006"},
						"val": 148
					},
					{
						"key": {"grade": "All", "subgroup": "African American", "year": "2006"},
						"val": 124
					},
					{
						"key": {"grade": "All", "subgroup": "White", "year": "2006"},
						"val": 19
					},
					{
						"key": {"grade": "All", "subgroup": "Male", "year": "2006"},
						"val": 77
					},
					{
						"key": {"grade": "All", "subgroup": "Female", "year": "2006"},
						"val": 71
					},
					{
						"key": {"grade": "KG", "subgroup": "All", "year": "2006"},
						"val": 86
					},
					{
						"key": {"grade": "KG", "subgroup": "African American", "year": "2006"},
						"val": 76
					},
					{
						"key": {"grade": "KG", "subgroup": "Male", "year": "2006"},
						"val": 45
					},
					{
						"key": {"grade": "KG", "subgroup": "Female", "year": "2006"},
						"val": 41
					},
					{
						"key": {"grade": "PK", "subgroup": "All", "year": "2006"},
						"val": 62
					},
					{
						"key": {"grade": "PK", "subgroup": "African American", "year": "2006"},
						"val": 48
					},
					{
						"key": {"grade": "PK", "subgroup": "White", "year": "2006"},
						"val": 10
					},
					{
						"key": {"grade": "PK", "subgroup": "Male", "year": "2006"},
						"val": 32
					},
					{
						"key": {"grade": "PK", "subgroup": "Female", "year": "2006"},
						"val": 30
					},
					{
						"key": {"grade": "All", "subgroup": "All", "year": "2009"},
						"val": 231
					},
					{
						"key": {"grade": "All", "subgroup": "African American", "year": "2009"},
						"val": 98
					},
					{
						"key": {"grade": "All", "subgroup": "White", "year": "2009"},
						"val": 119
					},
					{
						"key": {"grade": "All", "subgroup": "Economically Disadvantaged", "year": "2009"},
						"val": 50
					},
					{
						"key": {"grade": "All", "subgroup": "Male", "year": "2009"},
						"val": 107
					},
					{
						"key": {"grade": "All", "subgroup": "Female", "year": "2009"},
						"val": 124
					},
					{
						"key": {"grade": "PK", "subgroup": "All", "year": "2009"},
						"val": 99
					},
					{
						"key": {"grade": "PK", "subgroup": "African American", "year": "2009"},
						"val": 35
					},
					{
						"key": {"grade": "PK", "subgroup": "White", "year": "2009"},
						"val": 57
					},
					{
						"key": {"grade": "PK", "subgroup": "Economically Disadvantaged", "year": "2009"},
						"val": 18
					},
					{
						"key": {"grade": "PK", "subgroup": "Male", "year": "2009"},
						"val": 43
					},
					{
						"key": {"grade": "PK", "subgroup": "Female", "year": "2009"},
						"val": 56
					},
					{
						"key": {"grade": "KG", "subgroup": "All", "year": "2009"},
						"val": 117
					},
					{
						"key": {"grade": "KG", "subgroup": "African American", "year": "2009"},
						"val": 56
					},
					{
						"key": {"grade": "KG", "subgroup": "White", "year": "2009"},
						"val": 55
					},
					{
						"key": {"grade": "KG", "subgroup": "Economically Disadvantaged", "year": "2009"},
						"val": 29
					},
					{
						"key": {"grade": "KG", "subgroup": "Male", "year": "2009"},
						"val": 57
					},
					{
						"key": {"grade": "KG", "subgroup": "Female", "year": "2009"},
						"val": 60
					},
					{
						"key": {"grade": "PS", "subgroup": "All", "year": "2009"},
						"val": 15
					},
					{
						"key": {"grade": "All", "subgroup": "All", "year": "2004"},
						"val": 143
					},
					{
						"key": {"grade": "All", "subgroup": "African American", "year": "2004"},
						"val": 128
					},
					{
						"key": {"grade": "All", "subgroup": "White", "year": "2004"},
						"val": 11
					},
					{
						"key": {"grade": "All", "subgroup": "Male", "year": "2004"},
						"val": 68
					},
					{
						"key": {"grade": "All", "subgroup": "Female", "year": "2004"},
						"val": 75
					},
					{
						"key": {"grade": "PK", "subgroup": "All", "year": "2004"},
						"val": 65
					},
					{
						"key": {"grade": "PK", "subgroup": "African American", "year": "2004"},
						"val": 57
					},
					{
						"key": {"grade": "PK", "subgroup": "Male", "year": "2004"},
						"val": 32
					},
					{
						"key": {"grade": "PK", "subgroup": "Female", "year": "2004"},
						"val": 33
					},
					{
						"key": {"grade": "KG", "subgroup": "All", "year": "2004"},
						"val": 78
					},
					{
						"key": {"grade": "KG", "subgroup": "African American", "year": "2004"},
						"val": 71
					},
					{
						"key": {"grade": "KG", "subgroup": "Male", "year": "2004"},
						"val": 36
					},
					{
						"key": {"grade": "KG", "subgroup": "Female", "year": "2004"},
						"val": 42
					},
					{
						"key": {"grade": "All", "subgroup": "All", "year": "2013"},
						"val": 228
					},
					{
						"key": {"grade": "All", "subgroup": "African American", "year": "2013"},
						"val": 67
					},
					{
						"key": {"grade": "All", "subgroup": "White", "year": "2013"},
						"val": 134
					},
					{
						"key": {"grade": "All", "subgroup": "Hispanic", "year": "2013"},
						"val": 13
					},
					{
						"key": {"grade": "All", "subgroup": "Multi Racial", "year": "2013"},
						"val": 12
					},
					{
						"key": {"grade": "All", "subgroup": "Special Education", "year": "2013"},
						"val": 10
					},
					{
						"key": {"grade": "All", "subgroup": "Economically Disadvantaged", "year": "2013"},
						"val": 30
					},
					{
						"key": {"grade": "All", "subgroup": "Male", "year": "2013"},
						"val": 109
					},
					{
						"key": {"grade": "All", "subgroup": "Female", "year": "2013"},
						"val": 119
					},
					{
						"key": {"grade": "PK", "subgroup": "All", "year": "2013"},
						"val": 81
					},
					{
						"key": {"grade": "PK", "subgroup": "African American", "year": "2013"},
						"val": 26
					},
					{
						"key": {"grade": "PK", "subgroup": "White", "year": "2013"},
						"val": 46
					},
					{
						"key": {"grade": "PK", "subgroup": "Economically Disadvantaged", "year": "2013"},
						"val": 10
					},
					{
						"key": {"grade": "PK", "subgroup": "Male", "year": "2013"},
						"val": 34
					},
					{
						"key": {"grade": "PK", "subgroup": "Female", "year": "2013"},
						"val": 47
					},
					{
						"key": {"grade": "PS", "subgroup": "All", "year": "2013"},
						"val": 60
					},
					{
						"key": {"grade": "PS", "subgroup": "African American", "year": "2013"},
						"val": 11
					},
					{
						"key": {"grade": "PS", "subgroup": "White", "year": "2013"},
						"val": 40
					},
					{
						"key": {"grade": "PS", "subgroup": "Male", "year": "2013"},
						"val": 30
					},
					{
						"key": {"grade": "PS", "subgroup": "Female", "year": "2013"},
						"val": 30
					},
					{
						"key": {"grade": "KG", "subgroup": "All", "year": "2013"},
						"val": 87
					},
					{
						"key": {"grade": "KG", "subgroup": "African American", "year": "2013"},
						"val": 30
					},
					{
						"key": {"grade": "KG", "subgroup": "White", "year": "2013"},
						"val": 48
					},
					{
						"key": {"grade": "KG", "subgroup": "Economically Disadvantaged", "year": "2013"},
						"val": 12
					},
					{
						"key": {"grade": "KG", "subgroup": "Male", "year": "2013"},
						"val": 45
					},
					{
						"key": {"grade": "KG", "subgroup": "Female", "year": "2013"},
						"val": 42
					},
					{
						"key": {"grade": "All", "subgroup": "All", "year": "2010"},
						"val": 149
					},
					{
						"key": {"grade": "All", "subgroup": "African American", "year": "2010"},
						"val": 70
					},
					{
						"key": {"grade": "All", "subgroup": "White", "year": "2010"},
						"val": 62
					},
					{
						"key": {"grade": "All", "subgroup": "Economically Disadvantaged", "year": "2010"},
						"val": 41
					},
					{
						"key": {"grade": "All", "subgroup": "Male", "year": "2010"},
						"val": 72
					},
					{
						"key": {"grade": "All", "subgroup": "Female", "year": "2010"},
						"val": 77
					},
					{
						"key": {"grade": "PK", "subgroup": "All", "year": "2010"},
						"val": 57
					},
					{
						"key": {"grade": "PK", "subgroup": "African American", "year": "2010"},
						"val": 31
					},
					{
						"key": {"grade": "PK", "subgroup": "White", "year": "2010"},
						"val": 19
					},
					{
						"key": {"grade": "PK", "subgroup": "Economically Disadvantaged", "year": "2010"},
						"val": 16
					},
					{
						"key": {"grade": "PK", "subgroup": "Male", "year": "2010"},
						"val": 31
					},
					{
						"key": {"grade": "PK", "subgroup": "Female", "year": "2010"},
						"val": 26
					},
					{
						"key": {"grade": "PS", "subgroup": "All", "year": "2010"},
						"val": 30
					},
					{
						"key": {"grade": "PS", "subgroup": "White", "year": "2010"},
						"val": 20
					},
					{
						"key": {"grade": "PS", "subgroup": "Male", "year": "2010"},
						"val": 16
					},
					{
						"key": {"grade": "PS", "subgroup": "Female", "year": "2010"},
						"val": 14
					},
					{
						"key": {"grade": "KG", "subgroup": "All", "year": "2010"},
						"val": 62
					},
					{
						"key": {"grade": "KG", "subgroup": "African American", "year": "2010"},
						"val": 33
					},
					{
						"key": {"grade": "KG", "subgroup": "White", "year": "2010"},
						"val": 23
					},
					{
						"key": {"grade": "KG", "subgroup": "Economically Disadvantaged", "year": "2010"},
						"val": 21
					},
					{
						"key": {"grade": "KG", "subgroup": "Male", "year": "2010"},
						"val": 25
					},
					{
						"key": {"grade": "KG", "subgroup": "Female", "year": "2010"},
						"val": 37
					},
					{
						"key": {"grade": "All", "subgroup": "All", "year": "2007"},
						"val": 165
					},
					{
						"key": {"grade": "All", "subgroup": "African American", "year": "2007"},
						"val": 118
					},
					{
						"key": {"grade": "All", "subgroup": "White", "year": "2007"},
						"val": 37
					},
					{
						"key": {"grade": "All", "subgroup": "Male", "year": "2007"},
						"val": 90
					},
					{
						"key": {"grade": "All", "subgroup": "Female", "year": "2007"},
						"val": 75
					},
					{
						"key": {"grade": "PK", "subgroup": "All", "year": "2007"},
						"val": 66
					},
					{
						"key": {"grade": "PK", "subgroup": "African American", "year": "2007"},
						"val": 48
					},
					{
						"key": {"grade": "PK", "subgroup": "White", "year": "2007"},
						"val": 12
					},
					{
						"key": {"grade": "PK", "subgroup": "Male", "year": "2007"},
						"val": 37
					},
					{
						"key": {"grade": "PK", "subgroup": "Female", "year": "2007"},
						"val": 29
					},
					{
						"key": {"grade": "KG", "subgroup": "All", "year": "2007"},
						"val": 79
					},
					{
						"key": {"grade": "KG", "subgroup": "African American", "year": "2007"},
						"val": 60
					},
					{
						"key": {"grade": "KG", "subgroup": "White", "year": "2007"},
						"val": 15
					},
					{
						"key": {"grade": "KG", "subgroup": "Male", "year": "2007"},
						"val": 44
					},
					{
						"key": {"grade": "KG", "subgroup": "Female", "year": "2007"},
						"val": 35
					},
					{
						"key": {"grade": "PS", "subgroup": "All", "year": "2007"},
						"val": 20
					},
					{
						"key": {"grade": "PS", "subgroup": "African American", "year": "2007"},
						"val": 10
					},
					{
						"key": {"grade": "PS", "subgroup": "White", "year": "2007"},
						"val": 10
					},
					{
						"key": {"grade": "PS", "subgroup": "Female", "year": "2007"},
						"val": 11
					},
					{
						"key": {"grade": "All", "subgroup": "All", "year": "2008"},
						"val": 150
					},
					{
						"key": {"grade": "All", "subgroup": "African American", "year": "2008"},
						"val": 102
					},
					{
						"key": {"grade": "All", "subgroup": "White", "year": "2008"},
						"val": 41
					},
					{
						"key": {"grade": "All", "subgroup": "Economically Disadvantaged", "year": "2008"},
						"val": 48
					},
					{
						"key": {"grade": "All", "subgroup": "Male", "year": "2008"},
						"val": 76
					},
					{
						"key": {"grade": "All", "subgroup": "Female", "year": "2008"},
						"val": 70
					},
					{
						"key": {"grade": "PK", "subgroup": "All", "year": "2008"},
						"val": 71
					},
					{
						"key": {"grade": "PK", "subgroup": "African American", "year": "2008"},
						"val": 52
					},
					{
						"key": {"grade": "PK", "subgroup": "White", "year": "2008"},
						"val": 16
					},
					{
						"key": {"grade": "PK", "subgroup": "Economically Disadvantaged", "year": "2008"},
						"val": 21
					},
					{
						"key": {"grade": "PK", "subgroup": "Male", "year": "2008"},
						"val": 32
					},
					{
						"key": {"grade": "PK", "subgroup": "Female", "year": "2008"},
						"val": 37
					},
					{
						"key": {"grade": "KG", "subgroup": "All", "year": "2008"},
						"val": 64
					},
					{
						"key": {"grade": "KG", "subgroup": "African American", "year": "2008"},
						"val": 45
					},
					{
						"key": {"grade": "KG", "subgroup": "White", "year": "2008"},
						"val": 15
					},
					{
						"key": {"grade": "KG", "subgroup": "Economically Disadvantaged", "year": "2008"},
						"val": 25
					},
					{
						"key": {"grade": "KG", "subgroup": "Male", "year": "2008"},
						"val": 39
					},
					{
						"key": {"grade": "KG", "subgroup": "Female", "year": "2008"},
						"val": 24
					},
					{
						"key": {"grade": "PS", "subgroup": "All", "year": "2008"},
						"val": 15
					},
					{
						"key": {"grade": "PS", "subgroup": "White", "year": "2008"},
						"val": 10
					},
					{
						"key": {"grade": "All", "subgroup": "All", "year": "2005"},
						"val": 150
					},
					{
						"key": {"grade": "All", "subgroup": "African American", "year": "2005"},
						"val": 134
					},
					{
						"key": {"grade": "All", "subgroup": "White", "year": "2005"},
						"val": 11
					},
					{
						"key": {"grade": "All", "subgroup": "Economically Disadvantaged", "year": "2005"},
						"val": 20
					},
					{
						"key": {"grade": "All", "subgroup": "Male", "year": "2005"},
						"val": 71
					},
					{
						"key": {"grade": "All", "subgroup": "Female", "year": "2005"},
						"val": 77
					},
					{
						"key": {"grade": "KG", "subgroup": "All", "year": "2005"},
						"val": 84
					},
					{
						"key": {"grade": "KG", "subgroup": "African American", "year": "2005"},
						"val": 78
					},
					{
						"key": {"grade": "KG", "subgroup": "Economically Disadvantaged", "year": "2005"},
						"val": 10
					},
					{
						"key": {"grade": "KG", "subgroup": "Male", "year": "2005"},
						"val": 38
					},
					{
						"key": {"grade": "KG", "subgroup": "Female", "year": "2005"},
						"val": 45
					},
					{
						"key": {"grade": "PK", "subgroup": "All", "year": "2005"},
						"val": 66
					},
					{
						"key": {"grade": "PK", "subgroup": "African American", "year": "2005"},
						"val": 56
					},
					{
						"key": {"grade": "PK", "subgroup": "Economically Disadvantaged", "year": "2005"},
						"val": 10
					},
					{
						"key": {"grade": "PK", "subgroup": "Male", "year": "2005"},
						"val": 33
					},
					{
						"key": {"grade": "PK", "subgroup": "Female", "year": "2005"},
						"val": 32
					},
					{
						"key": {"grade": "All", "subgroup": "All", "year": "2012"},
						"val": 230
					},
					{
						"key": {"grade": "All", "subgroup": "African American", "year": "2012"},
						"val": 95
					},
					{
						"key": {"grade": "All", "subgroup": "White", "year": "2012"},
						"val": 106
					},
					{
						"key": {"grade": "All", "subgroup": "Multi Racial", "year": "2012"},
						"val": 16
					},
					{
						"key": {"grade": "All", "subgroup": "Special Education", "year": "2012"},
						"val": 15
					},
					{
						"key": {"grade": "All", "subgroup": "Economically Disadvantaged", "year": "2012"},
						"val": 63
					},
					{
						"key": {"grade": "All", "subgroup": "Male", "year": "2012"},
						"val": 116
					},
					{
						"key": {"grade": "All", "subgroup": "Female", "year": "2012"},
						"val": 114
					},
					{
						"key": {"grade": "KG", "subgroup": "All", "year": "2012"},
						"val": 105
					},
					{
						"key": {"grade": "KG", "subgroup": "African American", "year": "2012"},
						"val": 64
					},
					{
						"key": {"grade": "KG", "subgroup": "White", "year": "2012"},
						"val": 34
					},
					{
						"key": {"grade": "KG", "subgroup": "Special Education", "year": "2012"},
						"val": 11
					},
					{
						"key": {"grade": "KG", "subgroup": "Economically Disadvantaged", "year": "2012"},
						"val": 46
					},
					{
						"key": {"grade": "KG", "subgroup": "Male", "year": "2012"},
						"val": 52
					},
					{
						"key": {"grade": "KG", "subgroup": "Female", "year": "2012"},
						"val": 53
					},
					{
						"key": {"grade": "PK", "subgroup": "All", "year": "2012"},
						"val": 80
					},
					{
						"key": {"grade": "PK", "subgroup": "African American", "year": "2012"},
						"val": 27
					},
					{
						"key": {"grade": "PK", "subgroup": "White", "year": "2012"},
						"val": 40
					},
					{
						"key": {"grade": "PK", "subgroup": "Multi Racial", "year": "2012"},
						"val": 10
					},
					{
						"key": {"grade": "PK", "subgroup": "Economically Disadvantaged", "year": "2012"},
						"val": 14
					},
					{
						"key": {"grade": "PK", "subgroup": "Male", "year": "2012"},
						"val": 41
					},
					{
						"key": {"grade": "PK", "subgroup": "Female", "year": "2012"},
						"val": 39
					},
					{
						"key": {"grade": "PS", "subgroup": "All", "year": "2012"},
						"val": 45
					},
					{
						"key": {"grade": "PS", "subgroup": "White", "year": "2012"},
						"val": 32
					},
					{
						"key": {"grade": "PS", "subgroup": "Male", "year": "2012"},
						"val": 23
					},
					{
						"key": {"grade": "PS", "subgroup": "Female", "year": "2012"},
						"val": 22
					}
				]
			},
			{
				"id": "mgp_scores",
				"data": [

				]
			},
			{
				"id": "college_readiness",
				"data": [

				]
			},
			{
				"id": "special_ed",
				"data": [

				]
			},
			{
				"id": "unexcused_absences",
				"data": [
					{
						"key": {
							"year": "2012"
						},
						"val": {
							"1-5_days":53,
							"6-10_days":26,
							"11-15_days":6,
							"16-25_days":4,
							"more_than_25_days":2,
							"state_1-5_days":42,
							"state_6-10_days":23,
							"state_11-15_days":10,
							"state_16-25_days":8,
							"state_more_than_25_days":5
						}
					}
				]
			},
			{
				"id": "attendance",
				"data": [
					{
						"key": {
							"year": "2012"
						},
						"val": {
							"in_seat_attendance":0.96,
							"state_in_seat_attendance":0.91,
							"average_daily_attendance":null,
							"state_average_daily_attendance":null
						}
					}
				]
			},
			{
				"id": "suspensions",
				"data": [
					{
						"key": {
							"year": "2012",
							"subgroup": "All"
						},
						"val": {
							"suspended_1":0,
							"suspended_11":0,
							"state_suspended_1":0.01,
							"state_suspended_11":0
						}
					},
					{
						"key": {
							"year": "2012",
							"subgroup": "African American"
						},
						"val": {
							"suspended_1":0,
							"suspended_11":0,
							"state_suspended_1":0.02,
							"state_suspended_11":0
						}
					},
					{
						"key": {
							"year": "2012",
							"subgroup": "Economically Disadvantaged"
						},
						"val": {
							"suspended_1":0,
							"suspended_11":0,
							"state_suspended_1":0.02,
							"state_suspended_11":0
						}
					},
					{
						"key": {
							"year": "2012",
							"subgroup": "Multi Racial"
						},
						"val": {
							"suspended_1":0,
							"suspended_11":0,
							"state_suspended_1":0.01,
							"state_suspended_11":0
						}
					},
					{
						"key": {
							"year": "2012",
							"subgroup": "Special Education"
						},
						"val": {
							"suspended_1":0,
							"suspended_11":0,
							"state_suspended_1":0.02,
							"state_suspended_11":0
						}
					},
					{
						"key": {
							"year": "2012",
							"subgroup": "White"
						},
						"val": {
							"suspended_1":0,
							"suspended_11":0,
							"state_suspended_1":0.01,
							"state_suspended_11":0
						}
					}
				]
			},
			{
				"id": "expulsions",
				"data": [
					{
						"key": {
							"year": "2012"
						},
						"val": {
							"expulsions":0,
							"state_expulsions":2
						}
					}
				]
			},
			{
				"id": "mid_year_entry_and_withdrawal",
				"data": [
					{
						"key": {
							"year": "2012",
							"month": 4
						},
						"val": {
							"entry":0.01,
							"withdrawal":0,
							"net_cumulative":-0.01
						}
					},
					{
						"key": {
							"year": "2012",
							"month": 12
						},
						"val": {
							"entry":null,
							"withdrawal":null,
							"net_cumulative":0
						}
					},
					{
						"key": {
							"year": "2012",
							"month": 2
						},
						"val": {
							"entry":0,
							"withdrawal":0.01,
							"net_cumulative":-0.02
						}
					},
					{
						"key": {
							"year": "2012",
							"month": 1
						},
						"val": {
							"entry":0,
							"withdrawal":0.01,
							"net_cumulative":-0.01
						}
					},
					{
						"key": {
							"year": "2012",
							"month": 3
						},
						"val": {
							"entry":0,
							"withdrawal":0.01,
							"net_cumulative":-0.03
						}
					},
					{
						"key": {
							"year": "2012",
							"month": 5
						},
						"val": {
							"entry":0.02,
							"withdrawal":0,
							"net_cumulative":0.01
						}
					},
					{
						"key": {
							"year": "2012",
							"month": 11
						},
						"val": {
							"entry":0,
							"withdrawal":0,
							"net_cumulative":0
						}
					},
					{
						"key": {
							"year": "2012",
							"month": 10
						},
						"val": {
							"entry":0,
							"withdrawal":0,
							"net_cumulative":0
						}
					}
				]
			}
		]
	 }
}
