{
	"timestamp": "Fri Apr 04 15:17:45 2014",
	"org_type": "lea",
	"org_name": "Mundo Verde Bilingual PCS",
	"report_card": {
		"sections": [
			{
				"id": "dccas",
				"data": [

				]
			},
			{
				"id": "amo_targets",
				"data": [

				]
			},
			{
				"id": "hqt_status",
				"data":1
			},
			{
				"id": "graduation",
				"data": [


				]
			},
			{
				"id": "college_enroll",
				"data": [

				]
			}
		]
	 },


	"profile": {
		"sections": [
			{
				"id": "enrollment",
				"data": [
					{
						"key": {"grade": "All", "subgroup": "All", "year": "2011"},
						"val": 122
					},
					{
						"key": {"grade": "All", "subgroup": "African American", "year": "2011"},
						"val": 26
					},
					{
						"key": {"grade": "All", "subgroup": "White", "year": "2011"},
						"val": 43
					},
					{
						"key": {"grade": "All", "subgroup": "Hispanic", "year": "2011"},
						"val": 49
					},
					{
						"key": {"grade": "All", "subgroup": "English Learner", "year": "2011"},
						"val": 40
					},
					{
						"key": {"grade": "All", "subgroup": "Economically Disadvantaged", "year": "2011"},
						"val": 32
					},
					{
						"key": {"grade": "All", "subgroup": "Male", "year": "2011"},
						"val": 68
					},
					{
						"key": {"grade": "All", "subgroup": "Female", "year": "2011"},
						"val": 54
					},
					{
						"key": {"grade": "PS", "subgroup": "All", "year": "2011"},
						"val": 38
					},
					{
						"key": {"grade": "PS", "subgroup": "White", "year": "2011"},
						"val": 17
					},
					{
						"key": {"grade": "PS", "subgroup": "Hispanic", "year": "2011"},
						"val": 10
					},
					{
						"key": {"grade": "PS", "subgroup": "English Learner", "year": "2011"},
						"val": 11
					},
					{
						"key": {"grade": "PS", "subgroup": "Male", "year": "2011"},
						"val": 17
					},
					{
						"key": {"grade": "PS", "subgroup": "Female", "year": "2011"},
						"val": 21
					},
					{
						"key": {"grade": "KG", "subgroup": "All", "year": "2011"},
						"val": 46
					},
					{
						"key": {"grade": "KG", "subgroup": "African American", "year": "2011"},
						"val": 12
					},
					{
						"key": {"grade": "KG", "subgroup": "White", "year": "2011"},
						"val": 11
					},
					{
						"key": {"grade": "KG", "subgroup": "Hispanic", "year": "2011"},
						"val": 23
					},
					{
						"key": {"grade": "KG", "subgroup": "English Learner", "year": "2011"},
						"val": 17
					},
					{
						"key": {"grade": "KG", "subgroup": "Economically Disadvantaged", "year": "2011"},
						"val": 21
					},
					{
						"key": {"grade": "KG", "subgroup": "Male", "year": "2011"},
						"val": 25
					},
					{
						"key": {"grade": "KG", "subgroup": "Female", "year": "2011"},
						"val": 21
					},
					{
						"key": {"grade": "PK", "subgroup": "All", "year": "2011"},
						"val": 38
					},
					{
						"key": {"grade": "PK", "subgroup": "White", "year": "2011"},
						"val": 15
					},
					{
						"key": {"grade": "PK", "subgroup": "Hispanic", "year": "2011"},
						"val": 16
					},
					{
						"key": {"grade": "PK", "subgroup": "English Learner", "year": "2011"},
						"val": 12
					},
					{
						"key": {"grade": "PK", "subgroup": "Male", "year": "2011"},
						"val": 26
					},
					{
						"key": {"grade": "PK", "subgroup": "Female", "year": "2011"},
						"val": 12
					},
					{
						"key": {"grade": "All", "subgroup": "All", "year": "2012"},
						"val": 237
					},
					{
						"key": {"grade": "All", "subgroup": "African American", "year": "2012"},
						"val": 46
					},
					{
						"key": {"grade": "All", "subgroup": "White", "year": "2012"},
						"val": 65
					},
					{
						"key": {"grade": "All", "subgroup": "Hispanic", "year": "2012"},
						"val": 107
					},
					{
						"key": {"grade": "All", "subgroup": "Multi Racial", "year": "2012"},
						"val": 12
					},
					{
						"key": {"grade": "All", "subgroup": "Special Education", "year": "2012"},
						"val": 18
					},
					{
						"key": {"grade": "All", "subgroup": "English Learner", "year": "2012"},
						"val": 64
					},
					{
						"key": {"grade": "All", "subgroup": "Economically Disadvantaged", "year": "2012"},
						"val": 78
					},
					{
						"key": {"grade": "All", "subgroup": "Male", "year": "2012"},
						"val": 123
					},
					{
						"key": {"grade": "All", "subgroup": "Female", "year": "2012"},
						"val": 114
					},
					{
						"key": {"grade": "PS", "subgroup": "All", "year": "2012"},
						"val": 40
					},
					{
						"key": {"grade": "PS", "subgroup": "White", "year": "2012"},
						"val": 10
					},
					{
						"key": {"grade": "PS", "subgroup": "Hispanic", "year": "2012"},
						"val": 19
					},
					{
						"key": {"grade": "PS", "subgroup": "English Learner", "year": "2012"},
						"val": 10
					},
					{
						"key": {"grade": "PS", "subgroup": "Male", "year": "2012"},
						"val": 20
					},
					{
						"key": {"grade": "PS", "subgroup": "Female", "year": "2012"},
						"val": 20
					},
					{
						"key": {"grade": "KG", "subgroup": "All", "year": "2012"},
						"val": 69
					},
					{
						"key": {"grade": "KG", "subgroup": "White", "year": "2012"},
						"val": 21
					},
					{
						"key": {"grade": "KG", "subgroup": "Hispanic", "year": "2012"},
						"val": 32
					},
					{
						"key": {"grade": "KG", "subgroup": "English Learner", "year": "2012"},
						"val": 22
					},
					{
						"key": {"grade": "KG", "subgroup": "Economically Disadvantaged", "year": "2012"},
						"val": 24
					},
					{
						"key": {"grade": "KG", "subgroup": "Male", "year": "2012"},
						"val": 42
					},
					{
						"key": {"grade": "KG", "subgroup": "Female", "year": "2012"},
						"val": 27
					},
					{
						"key": {"grade": "01", "subgroup": "All", "year": "2012"},
						"val": 64
					},
					{
						"key": {"grade": "01", "subgroup": "African American", "year": "2012"},
						"val": 17
					},
					{
						"key": {"grade": "01", "subgroup": "Hispanic", "year": "2012"},
						"val": 35
					},
					{
						"key": {"grade": "01", "subgroup": "English Learner", "year": "2012"},
						"val": 11
					},
					{
						"key": {"grade": "01", "subgroup": "Economically Disadvantaged", "year": "2012"},
						"val": 31
					},
					{
						"key": {"grade": "01", "subgroup": "Male", "year": "2012"},
						"val": 35
					},
					{
						"key": {"grade": "01", "subgroup": "Female", "year": "2012"},
						"val": 29
					},
					{
						"key": {"grade": "PK", "subgroup": "All", "year": "2012"},
						"val": 64
					},
					{
						"key": {"grade": "PK", "subgroup": "African American", "year": "2012"},
						"val": 14
					},
					{
						"key": {"grade": "PK", "subgroup": "White", "year": "2012"},
						"val": 25
					},
					{
						"key": {"grade": "PK", "subgroup": "Hispanic", "year": "2012"},
						"val": 21
					},
					{
						"key": {"grade": "PK", "subgroup": "English Learner", "year": "2012"},
						"val": 21
					},
					{
						"key": {"grade": "PK", "subgroup": "Economically Disadvantaged", "year": "2012"},
						"val": 15
					},
					{
						"key": {"grade": "PK", "subgroup": "Male", "year": "2012"},
						"val": 26
					},
					{
						"key": {"grade": "PK", "subgroup": "Female", "year": "2012"},
						"val": 38
					},
					{
						"key": {"grade": "All", "subgroup": "All", "year": "2013"},
						"val": 274
					},
					{
						"key": {"grade": "All", "subgroup": "African American", "year": "2013"},
						"val": 55
					},
					{
						"key": {"grade": "All", "subgroup": "White", "year": "2013"},
						"val": 81
					},
					{
						"key": {"grade": "All", "subgroup": "Hispanic", "year": "2013"},
						"val": 123
					},
					{
						"key": {"grade": "All", "subgroup": "Multi Racial", "year": "2013"},
						"val": 11
					},
					{
						"key": {"grade": "All", "subgroup": "Special Education", "year": "2013"},
						"val": 18
					},
					{
						"key": {"grade": "All", "subgroup": "English Learner", "year": "2013"},
						"val": 76
					},
					{
						"key": {"grade": "All", "subgroup": "Economically Disadvantaged", "year": "2013"},
						"val": 93
					},
					{
						"key": {"grade": "All", "subgroup": "Male", "year": "2013"},
						"val": 141
					},
					{
						"key": {"grade": "All", "subgroup": "Female", "year": "2013"},
						"val": 133
					},
					{
						"key": {"grade": "02", "subgroup": "All", "year": "2013"},
						"val": 69
					},
					{
						"key": {"grade": "02", "subgroup": "African American", "year": "2013"},
						"val": 22
					},
					{
						"key": {"grade": "02", "subgroup": "White", "year": "2013"},
						"val": 11
					},
					{
						"key": {"grade": "02", "subgroup": "Hispanic", "year": "2013"},
						"val": 34
					},
					{
						"key": {"grade": "02", "subgroup": "English Learner", "year": "2013"},
						"val": 12
					},
					{
						"key": {"grade": "02", "subgroup": "Economically Disadvantaged", "year": "2013"},
						"val": 30
					},
					{
						"key": {"grade": "02", "subgroup": "Male", "year": "2013"},
						"val": 40
					},
					{
						"key": {"grade": "02", "subgroup": "Female", "year": "2013"},
						"val": 29
					},
					{
						"key": {"grade": "PS", "subgroup": "All", "year": "2013"},
						"val": 20
					},
					{
						"key": {"grade": "PS", "subgroup": "English Learner", "year": "2013"},
						"val": 11
					},
					{
						"key": {"grade": "PS", "subgroup": "Female", "year": "2013"},
						"val": 12
					},
					{
						"key": {"grade": "KG", "subgroup": "All", "year": "2013"},
						"val": 67
					},
					{
						"key": {"grade": "KG", "subgroup": "African American", "year": "2013"},
						"val": 13
					},
					{
						"key": {"grade": "KG", "subgroup": "White", "year": "2013"},
						"val": 25
					},
					{
						"key": {"grade": "KG", "subgroup": "Hispanic", "year": "2013"},
						"val": 26
					},
					{
						"key": {"grade": "KG", "subgroup": "English Learner", "year": "2013"},
						"val": 21
					},
					{
						"key": {"grade": "KG", "subgroup": "Economically Disadvantaged", "year": "2013"},
						"val": 22
					},
					{
						"key": {"grade": "KG", "subgroup": "Male", "year": "2013"},
						"val": 26
					},
					{
						"key": {"grade": "KG", "subgroup": "Female", "year": "2013"},
						"val": 41
					},
					{
						"key": {"grade": "PK", "subgroup": "All", "year": "2013"},
						"val": 43
					},
					{
						"key": {"grade": "PK", "subgroup": "White", "year": "2013"},
						"val": 13
					},
					{
						"key": {"grade": "PK", "subgroup": "Hispanic", "year": "2013"},
						"val": 19
					},
					{
						"key": {"grade": "PK", "subgroup": "English Learner", "year": "2013"},
						"val": 10
					},
					{
						"key": {"grade": "PK", "subgroup": "Economically Disadvantaged", "year": "2013"},
						"val": 10
					},
					{
						"key": {"grade": "PK", "subgroup": "Male", "year": "2013"},
						"val": 21
					},
					{
						"key": {"grade": "PK", "subgroup": "Female", "year": "2013"},
						"val": 22
					},
					{
						"key": {"grade": "01", "subgroup": "All", "year": "2013"},
						"val": 75
					},
					{
						"key": {"grade": "01", "subgroup": "African American", "year": "2013"},
						"val": 12
					},
					{
						"key": {"grade": "01", "subgroup": "White", "year": "2013"},
						"val": 23
					},
					{
						"key": {"grade": "01", "subgroup": "Hispanic", "year": "2013"},
						"val": 35
					},
					{
						"key": {"grade": "01", "subgroup": "English Learner", "year": "2013"},
						"val": 22
					},
					{
						"key": {"grade": "01", "subgroup": "Economically Disadvantaged", "year": "2013"},
						"val": 25
					},
					{
						"key": {"grade": "01", "subgroup": "Male", "year": "2013"},
						"val": 46
					},
					{
						"key": {"grade": "01", "subgroup": "Female", "year": "2013"},
						"val": 29
					}
				]
			},
			{
				"id": "mgp_scores",
				"data": [

				]
			},
			{
				"id": "college_readiness",
				"data": [

				]
			},
			{
				"id": "special_ed",
				"data": [

				]
			}
		]
	 }
}
